.gitignore
MANIFEST.in
README.rst
setup.cfg
setup.py
docs/HISTORY.txt
raptus/__init__.py
raptus.contenttemplates.egg-info/PKG-INFO
raptus.contenttemplates.egg-info/SOURCES.txt
raptus.contenttemplates.egg-info/dependency_links.txt
raptus.contenttemplates.egg-info/entry_points.txt
raptus.contenttemplates.egg-info/namespace_packages.txt
raptus.contenttemplates.egg-info/not-zip-safe
raptus.contenttemplates.egg-info/requires.txt
raptus.contenttemplates.egg-info/top_level.txt
raptus/contenttemplates/__init__.py
raptus/contenttemplates/actions.py
raptus/contenttemplates/configure.zcml
raptus/contenttemplates/executor.py
raptus/contenttemplates/interfaces.py
raptus/contenttemplates/plone3.py
raptus/contenttemplates/traverser.py
raptus/contenttemplates/browser/__init__.py
raptus/contenttemplates/browser/configure.zcml
raptus/contenttemplates/browser/contenttemplates.py
raptus/contenttemplates/browser/form.py
raptus/contenttemplates/browser/interfaces.py
raptus/contenttemplates/browser/menu.py
raptus/contenttemplates/browser/templates/contenttemplates.pt
raptus/contenttemplates/browser/templates/form.pt
raptus/contenttemplates/i18n/raptus.contenttemplates-de.mo
raptus/contenttemplates/i18n/raptus.contenttemplates-de.po
raptus/contenttemplates/i18n/raptus.contenttemplates.pot