Metadata-Version: 1.0
Name: raptus.contenttemplates
Version: 1.0b3
Summary: Provides generic interfaces to create content templates using adapters
Home-page: https://github.com/Raptus/raptus.contenttemplates
Author: Raptus AG
Author-email: dev@raptus.com
License: GPL
Platform: UNKNOWN
Classifier: Programming Language :: Python
Classifier: Topic :: Software Development :: Libraries :: Python Modules
